MANIFEST.in
VERSION.txt
requirements.txt
setup.cfg
setup.py
ava_engine/__init__.py
ava_engine.egg-info/PKG-INFO
ava_engine.egg-info/SOURCES.txt
ava_engine.egg-info/dependency_links.txt
ava_engine.egg-info/requires.txt
ava_engine.egg-info/top_level.txt
ava_engine/ava/engine_api_pb2.py
ava_engine/ava/engine_core_pb2.py
ava_engine/ava/feature_classification_pb2.py
ava_engine/ava/feature_detection_pb2.py
ava_engine/ava/feature_face_recognition_pb2.py
ava_engine/ava/feeds_api_pb2.py
ava_engine/ava/images_api_pb2.py
ava_engine/ava/service_api_pb2.py
ava_engine/ava/service_api_pb2_grpc.py