Metadata-Version: 1.1
Name: ava-engine
Version: 0.6.2
Summary: Official Ava Engine Python SDK.
Home-page: UNKNOWN
Author: Image Intelligence
Author-email: support@imageintelligence.com
License: UNKNOWN
Platform: UNKNOWN
Classifier: Intended Audience :: Developers
Classifier: Programming Language :: Python :: 3 :: Only
Classifier: Programming Language :: Python :: 3.5
Classifier: Programming Language :: Python :: 3.6
